{"B+e6Wr65PR4IYN0zV2QoIA==":"header.svg.2022-05-19-18-46-09.0.png","mTRfcGH3ewg5w84kjYGPQg==":"pino.png","obdtuW2lHwSCWKYoOQfy9g==":"mbr.jpg","70nrvAhvZ+PSp8DBS4ttKg==":"intro.gif","PEZScfKepE/vxp2QURe+YA==":"mbr.png","rF/LAPwe5iZ4Xbpeg9STng==":"mbr-1.jpg","H7SiJv8d/QgrrQnzxRqqUg==":"mbr-1.png","6DKVq8e+Lh5RaqbL75xOmA==":"mbr-2.png","nVUI+HokZMf9xzX+qX0D7Q==":"mbr-3.png","di3cSOtF/Zt2T7k7e/vNWA==":"mbr-4.png","t6E1Rt4gnfJPUteSzeLO0g==":"mbr-5.png","Zj0AZtaaN2hzZCQPNvOd8g==":"mbr-6.png","W9QiD6STtxnWalMYVBB+Pg==":"mbr-7.png","PxkzUGUsRRK6TTTSz/qEyQ==":"mbr-8.png","QjrxjyPx93EAPDX/EulOYQ==":"360-f-222830795-mgoojvtdmwgcnbxthtf1a1zbqjikzbgc.jpg","+bqD+n8qjQa7i8lMvMDabw==":"mbr-2.jpg","gOkHDB2jt1cbZle+E4a4Aw==":"mbr-2.jpeg","YjK+fNxQG0fMym8S0uY7Sg==":"mbr-3.jpeg","/xIIh4h9hWWvepcY4pbypA==":"networking-100733179-large.jpg.webp","Xnoju8J0jw4CWPEdj17m+A==":"listen-network-banner-alina-grubnyak-unsplash-1024x328.jpg","7A+f01sZq34YnDNkt4mTqw==":"networks-icon-5.jpg.png","7lzcA58sIkH76HFpJsFQoA==":"networks-icon-5.jpg-1.png","1orl5H8Oq3c5Ntu9zi2dbw==":"neural-network-icon-3.jpg.png","K/8A2w9qSKf8HlN6i64elA==":"neural-network-icon-3.jpg-1.png","I18kD9/o+9rx7GrzAuHPAw==":"network.png","Rtynglhb2se9oLQOmeHoIA==":"pino-1.png","pPaMjBEnWEyaMVrNyYVXKg==":"pino2.png","j0p6w1/u31gu/utIEKxl9g==":"pino2-1.png","xQE4/DE75Fh5xZ07YZ7Kww==":"pino3.png","t6aGj0FDFvQCW23rAAwZ0w==":"eurasian-spoonbill-common-spoonbill-platalea-leucorodia-fly-37928726.jpg","YU+ML7TdH9coryiyEeweOw==":"unknown.jpg","2/mkVoIXsOZ+j2DB0XzSPQ==":"unknown.jpeg","f/UeU1CWjN8I6tclkbcmEg==":"images.jpeg","RWBXrlD+huqFKtNsRILrQg==":"eurasian-spoonbill-common-spoonbill-platalea-leucorodia-fly-37928726.jpeg","gR87Qj/HPwCiSbDJprz6NQ==":"diapositiva1.jpeg","HDep+mxFcoSZePRHyTNv7Q==":"diapositiva1-1.jpeg","NUTBDhk2c6Tuq/rXvsLgrg==":"diapositiva1-2.jpeg","vq17Hxy6gxWkjWFfQZwxAg==":"conn.jpg","2mEks6F8I8BmR4I3/ScPuQ==":"mbr-3.jpg","MzL3XCOfI37stXP/jiPKCA==":"0ia1nm8j_400x400-2-369x369.png","sJC5wdYqvpGowzJfedZYmQ==":"bioarchive-logo-2-506x316.png","Ns/4e9iqK49uv0fAiXjNXw==":"bioarchive-logo-1-506x316.png","gdAXt7H8xeXltpEQEg+E/w==":"scirep-284x177.png","uKRSWNFEs0X3C6Xux6U9LA==":"diapositiva1-540x304.jpg","remu8qfodfXrEYFyNgUQsg==":"diapositiva1-1-540x304.jpg","+toEwApjn3rVLQ66pbCsHg==":"x23524855-563x349.jpg","7Ml8KjmWrXVx7XK2H6cuHQ==":"diapositiva1-2-525x295.jpg","8CJNl5eg47Jd64hgF5u/wQ==":"diapositiva1-4-540x304.jpg","UFG7aobLMtU5/NvCONJYRA==":"diapositiva1-3-540x304.jpg","xvsxDKKIVaCu0ROw1KVpjA==":"diapositiva1-5-540x304.jpg","fNA0T/t2uh4L9FPKlvf3tA==":"diapositiva1-6-540x304.jpg","WX4ANXd8MFUwGxQlc47asg==":"diapositiva1-7-540x304.jpg","GiRHU/QlPyq+SW5nKcL5eg==":"diapositiva1-8-540x304.jpg","2xJaC9gZjfRkhjr73HJWjw==":"diapositiva1-9-540x304.jpg","R0wN0zZzkPCliw5+BJc72g==":"diapositiva1-10-540x304.jpg","WlYZtGtGCjEPF++rZlJbow==":"diapositiva1-11-540x304.jpg","iGGjem4OFpuKzEBmzPgq1Q==":"diapositiva1-12-540x304.jpg","mcGtw58BWMpkoemXcrz6ww==":"diapositiva1-13-540x304.jpg","1eLiGZA8l8fVrIEDWu2wHA==":"diapositiva1-14-540x304.jpg","GEljcFGbmiWODL3IB/V0gg==":"diapositiva1-17-517x291.jpg","t4vkyxi3HQTf8Y2ULfCBiQ==":"diapositiva1-18-376x211.jpg","u7I40np0trELsB7XgGT+Kg==":"diapositiva1-15-664x373.jpg","MYys0u0/uFxhkcaEQiSfNw==":"diapositiva1-16-647x364.jpg","ibuuPhXJaPjfsoWvHacGWg==":"diapositiva1-19-506x285.jpg","ESWz9JHEmrxndaDR0Y61mQ==":"diapositiva1-20-540x304.jpg","zbO1ymR0zFVUIvH9Z/YmGQ==":"diapositiva1-21-540x304.jpg","Vb7GgbMoe0curpGYBParsg==":"background3.jpg","FbDESUYGyzgY/ZWUGFvM2g==":"productflyer-231-506x338.png","BnCW57mYRTZT1clLeYNd0A==":"diapositiva1-506x285.png","guchllULIdduLRt9HhZJgw==":"bird-migration-eastern-hemisphere-published-2004.jpg","tZtVe0pYJkz1q1kfcroTJA==":"schermata-2022-07-08-alle-10.59.19.png","oRykAiO0rUD++7AmPeEwUg==":"background1.jpg","ZhJf8gmJ3bmBiWos26oy+A==":"figure2.jpg","C2OSv4TJBkgoW7X9p9oisw==":"senza-nome-2.jpg","sEBWwniWMlkfjPTfIDqG3A==":"fais-et-al.-2020-meiofauna-metabarcoding-in-lima-estuary-portugal-suggests-high-taxon-replacement-within-a-background-of-network-s-trascinato.jpg","dshAvKUj0IByB8n++Fzdcw==":"bellisario-et-al.-2021-the-network-structure-of-intertidal-meiofaunal-communities-from-environmental-dna-metabarcoding-surveys-in-no-trascinato.jpg","Y/oQqibAjnbq4A6T3HAykA==":"santoro-et-al-2020-host-biological-factors-and-geographic-locality-influence-predictors-of-trascinato.jpg","xgR9P/3IYOCjFD4rJMcjBg==":"santoro-et-al-2021-a-molecular-and-ecological-study-of-grillotia-cestoda-trascinato.jpg","vTrDvMD+Vs4lysHzYFONiQ==":"img-215-952x715.jpeg","wEc2BEAI9Z7cimQ0svchOg==":"img-215-952x715.jpg","8XgXWKKMwhb+qxOD/YTa5g==":"x23524855-576x768.jpeg","nXk9UzAjVdVoUkIfwyNusA==":"bioarchive-logo-676x423.png","7vw8LH2xOE6w0MerueyYZQ==":"background4.jpg","UwKnF2KLr/ocdf9gues7Jg==":"background5.jpg","pvFzbO7+CDtIsRO3CH6QSA==":"0001-1627490588260-copia.jpg","FTmRC55FpUT/oAFPVmqIdA==":"0027.jpg","qRuYhGJT7n4DI4n+Cef2LA==":"0027.jpeg","CJOd/k3wkD9NUnk5b/juzA==":"x09291393.jpg","f63ZhUV+q76H6QJZOgPI8w==":"x09291393.jpeg","BUlbx1GCJuGYhmCAm4x4oA==":"x09291393-1.jpeg","s4J9PlgIVlLBMv+b9jyPMw==":"adobestock-552748421-scaled.jpeg","9Ha82KjzDsejHXoIZLORxw==":"adobestock-552748421-scaled.png","7N0XYBpSD1AKMflA/NK+ag==":"royopensci-logo1.png","wX6A4xdyljoJekAmPaCsqg==":"images.png","MetttV01cQfnqc6E5t0MvA==":"figure3.jpg","ftwpcmcmyXbq33E/aEqo9g==":"royopensci-logo1-1.png","8J+7ksyRMUdj5Bz1l6CNCA==":"img-3.png","Q3Iy98t36yM/pkqXwvrg8Q==":"background7.jpg","uyLAvITkZG6RlBIA0vGZgw==":"logo-1.png","MR0MnYvKf0aa8/Dd5U5Wng==":"index.png","WcknznMXhFkhEjj3pqgM4A==":"index-1.png","6ak3hX++VNuW9UMgDpcadw==":"index.svg","rJRaKD8WVI2UVV7dc5uGEA==":"index-2.png","5tfz4lBwW0PQqsCWptwLJQ==":"g17.png","1IbireCzzQtpge038Z/jRQ==":"g17-1.png","a4foTUq7FtwpEZIlsGT++A==":"index-3.png","6iJyJ90xfYHT0OgHs3uvYg==":"index-4.png","+VJpJFING3RBrX1sZQpweg==":"index-1.svg","HmkKDhVnxWenyJp/04jTRA==":"index-5.png","LDDBHApFXEo/OxufvqdPOQ==":"badges.altmetric.com.png","ySbZkhtD1+OZ+wpSL2By2g==":"badges.altmetric.com-1.png","ak/qREtvnmqKaULRWrn3xQ==":"badges.altmetric.com-2.png","ia8762pIVEW5z4DVF+9Pag==":"altmetric-rgb.png","ZyH+Vdfa2EgkUZ5Sxjhk8A==":"caprellidae.jpg","DpuDCzLbXH3MVu95y3oT7Q==":"oriole-jpg.jpg","h4J1OnKnRHq4yyb0tCse4g==":"posidonia-oceanica-e1611760954897.jpg","qJbCX21FxQsDoGVOMKYDtw==":"slideshow-1595346087.jpg","XvbeLAwNVoh0IypO9S/DUQ==":"product4.jpg","gu39Oa5dFxvBr3qd9wTlrg==":"product5.jpg","PDbDIgnfNNfM0A/Qjxy4xw==":"product6.jpg","n1dx+NZv3qks526xC0hZ5Q==":"background13.jpg"}